pose_format/__init__.py
pose_format/pose.py
pose_format/pose_body.py
pose_format/pose_header.py
pose_format/pose_representation.py
pose_format/pose_visualizer.py
pose_format/bin/__init__.py
pose_format/bin/directory.py
pose_format/bin/pose_estimation.py
pose_format/bin/pose_info.py
pose_format/bin/pose_visualizer.py
pose_format/numpy/__init__.py
pose_format/numpy/pose_body.py
pose_format/numpy/representation/__init__.py
pose_format/numpy/representation/distance.py
pose_format/numpy/representation/distance_test.py
pose_format/tensorflow/__init__.py
pose_format/tensorflow/pose_body.py
pose_format/tensorflow/pose_body_test.py
pose_format/tensorflow/pose_representation.py
pose_format/tensorflow/pose_representation_test.py
pose_format/tensorflow/masked/__init__.py
pose_format/tensorflow/masked/tensor.py
pose_format/tensorflow/masked/tensor_graph_mode_test.py
pose_format/tensorflow/masked/tensor_test.py
pose_format/tensorflow/masked/tensorflow.py
pose_format/tensorflow/masked/tensorflow_test.py
pose_format/tensorflow/representation/__init__.py
pose_format/tensorflow/representation/angle.py
pose_format/tensorflow/representation/angle_test.py
pose_format/tensorflow/representation/distance.py
pose_format/tensorflow/representation/distance_test.py
pose_format/tensorflow/representation/inner_angle.py
pose_format/tensorflow/representation/inner_angle_test.py
pose_format/tensorflow/representation/point_line_distance.py
pose_format/tensorflow/representation/point_line_distance_test.py
pose_format/testing/__init__.py
pose_format/torch/__init__.py
pose_format/torch/pose_body.py
pose_format/torch/pose_representation.py
pose_format/torch/masked/__init__.py
pose_format/torch/masked/collator.py
pose_format/torch/masked/tensor.py
pose_format/torch/masked/torch.py
pose_format/torch/masked/torch_test.py
pose_format/torch/representation/__init__.py
pose_format/torch/representation/angle.py
pose_format/torch/representation/angle_test.py
pose_format/torch/representation/distance.py
pose_format-0.11.0.dist-info/METADATA
pose_format-0.11.0.dist-info/WHEEL
pose_format-0.11.0.dist-info/entry_points.txt
pose_format-0.11.0.dist-info/top_level.txt
pose_format-0.11.0.dist-info/RECORD
