Metadata-Version: 2.4
Name: pose_format
Version: 0.11.0
Summary: Library for viewing, augmenting, and handling .pose files
Author-email: Amit Moryossef <amitmoryossef@gmail.com>, Mathias Müller <anon1@ymous.com>, Rebecka Fahrni <anon2@ymous.com>
Keywords: Pose Files,Pose Interpolation,Pose Augmentation
Requires-Python: >=3.8
Requires-Dist: numpy
Requires-Dist: scipy
Requires-Dist: tqdm
Requires-Dist: simple-video-utils
Provides-Extra: dev
Requires-Dist: pylint; extra == "dev"
Requires-Dist: pytest; extra == "dev"
Requires-Dist: opencv-python; extra == "dev"
Requires-Dist: vidgear; extra == "dev"
Requires-Dist: mediapipe; extra == "dev"
Requires-Dist: torch; extra == "dev"
Requires-Dist: tensorflow; extra == "dev"
Requires-Dist: matplotlib; extra == "dev"
Provides-Extra: mediapipe
Requires-Dist: mediapipe<0.10.30; extra == "mediapipe"
